beliefppg/__init__.py
beliefppg/datasets/__init__.py
beliefppg/datasets/file_reader.py
beliefppg/datasets/pipeline_generator.py
beliefppg/inference/__init__.py
beliefppg/inference/inference.py
beliefppg/inference/inference_model_architecture.json
beliefppg/inference/inference_model_notimebackbone_architecture.json
beliefppg/inference/inference_model_notimebackbone_weights.npz
beliefppg/inference/inference_model_weights.npz
beliefppg/model/__init__.py
beliefppg/model/belief_ppg.py
beliefppg/model/binned_regression_loss.py
beliefppg/model/config.py
beliefppg/model/load.py
beliefppg/model/positional_encoding.py
beliefppg/model/prior_layer.py
beliefppg/model/timedomain_backbone.py
beliefppg/util/__init__.py
beliefppg/util/args.py
beliefppg/util/augmentations.py
beliefppg/util/callbacks.py
beliefppg/util/preprocessing.py
beliefppg-0.3.1.dist-info/LICENSE
beliefppg-0.3.1.dist-info/METADATA
beliefppg-0.3.1.dist-info/WHEEL
beliefppg-0.3.1.dist-info/top_level.txt
beliefppg-0.3.1.dist-info/RECORD
