Metadata-Version: 2.1
Name: beliefppg
Version: 0.3.1
Summary: Taking multi-channel PPG and Accelerometer signals as input, BeliefPPG predicts the instantaneous heart rate and provides an uncertainty estimate for the prediction.
Home-page: https://github.com/eth-siplab/BeliefPPG
Author: Paul Streli
Author-email: paul.streli@inf.ethz.ch
Keywords: PPG,heart rate,signal processing,uncertainty estimation,biomedical signals
Classifier: Development Status :: 4 - Beta
Classifier: Intended Audience :: Developers
Classifier: License :: OSI Approved :: MIT License
Classifier: Programming Language :: Python :: 3
Classifier: Programming Language :: Python :: 3.9
Classifier: Programming Language :: Python :: 3.10
Classifier: Programming Language :: Python :: 3.11
Classifier: Programming Language :: Python :: 3.12
Classifier: Topic :: Software Development :: Libraries
Requires-Python: >=3.9
License-File: LICENSE
Requires-Dist: numpy
Requires-Dist: pandas
Requires-Dist: scikit-learn
Requires-Dist: tensorflow >=2.14.0
Requires-Dist: tf-keras
Requires-Dist: tensorflow-probability ~=0.22.1
Requires-Dist: wandb
